neterraproxy/__init__.py
neterraproxy/__main__.py
neterraproxy/channels.json
neterraproxy/downloadepg.py
neterraproxy/neterra.py
neterraproxy/startnetman.py
neterraproxy/wsrv.py
neterraproxy-0.3.0.dist-info/LICENSE
neterraproxy-0.3.0.dist-info/METADATA
neterraproxy-0.3.0.dist-info/WHEEL
neterraproxy-0.3.0.dist-info/top_level.txt
neterraproxy-0.3.0.dist-info/RECORD
