Metadata-Version: 2.1
Name: neterraproxy
Version: 0.3.0
Summary: A python version of the neterra proxy java app written by @sgloutnikov
Home-page: https://github.com/ananchev/neterraproxy
Author: Anton Nanchev
Author-email: ananchev@gmail.com
Classifier: Programming Language :: Python :: 3
Classifier: License :: OSI Approved :: MIT License
Classifier: Operating System :: OS Independent
License-File: LICENSE
Requires-Dist: requests
Requires-Dist: bs4
Requires-Dist: apscheduler
